LICENSE
MANIFEST.in
README.rst
setup.py
djcharme/__init__.py
djcharme/admin.py
djcharme/charme_middleware.py
djcharme/charme_security_model.py
djcharme/errors.py
djcharme/exception.py
djcharme/forms.py
djcharme/local_settings.py.ini
djcharme/manage.py
djcharme/models.py
djcharme/security_middleware.py
djcharme/settings.py
djcharme/urls.py
djcharme/wsgi.py
djcharme.egg-info/PKG-INFO
djcharme.egg-info/SOURCES.txt
djcharme.egg-info/dependency_links.txt
djcharme.egg-info/not-zip-safe
djcharme.egg-info/requires.txt
djcharme.egg-info/top_level.txt
djcharme/migrations/0001_initial.py
djcharme/migrations/0002_remove_organizationuser_following.py
djcharme/migrations/0003_organizationuser_following.py
djcharme/migrations/__init__.py
djcharme/node/__init__.py
djcharme/node/actions.py
djcharme/node/constants.py
djcharme/node/doi.py
djcharme/node/model_queries.py
djcharme/node/sample.py
djcharme/node/search.py
djcharme/node/triple_queries.py
djcharme/opensearch/__init__.py
djcharme/opensearch/cimpl.py
djcharme/opensearch/os_conf.py
djcharme/resources/ceda_citations_to_metadata_url_mappings.csv
djcharme/resources/dataset_to_ceda_mappings.csv
djcharme/resources/djcharme_wsgi.conf
djcharme/resources/pylintrc
djcharme/resources/wsgi.py
djcharme/static/robots.txt
djcharme/static/charme/jsonld.js
djcharme/static/charme/css/charme.css
djcharme/static/charme/rdf/DCTypesVocab.js
djcharme/static/charme/rdf/OABody.js
djcharme/static/charme/rdf/OATarget.js
djcharme/static/charme/rdf/TextualBody.js
djcharme/static/charme/rdf/templates/DCTypesVocab.html
djcharme/static/charme/rdf/templates/OABody.html
djcharme/static/charme/rdf/templates/OATarget.html
djcharme/static/charme/rdf/templates/TextualBody.html
djcharme/static/charme/rdf/templates/Triple.html
djcharme/templates/400.html
djcharme/templates/404.html
djcharme/templates/500.html
djcharme/templates/503.html
djcharme/templates/charme_base.html
djcharme/templates/compose_annotation.html
djcharme/templates/conditions_of_use.html
djcharme/templates/facets_test.html
djcharme/templates/index.html
djcharme/templates/oauth_test2.html
djcharme/templates/responseTemplate.html
djcharme/templates/token_response.html
