Metadata-Version: 1.1
Name: djcharme
Version: 0.8.6
Summary: CHARMe Node
Home-page: https://github.com/CHARMe-Project/djcharme
Author: Antony Wilson
Author-email: antony.wilson@stfc.ac.uk
License: BSD licence, see LICENCE
Platform: UNKNOWN
Classifier: Framework :: Django :: 1.7
Classifier: License :: OSI Approved :: BSD License
Classifier: Natural Language :: English
Classifier: Programming Language :: Python :: 2.7
Classifier: Topic :: Internet :: WWW/HTTP :: HTTP Servers
